mparticle/__init__.py
mparticle/api_client.py
mparticle/configuration.py
mparticle/rest.py
mparticle/apis/__init__.py
mparticle/apis/events_api.py
mparticle/models/__init__.py
mparticle/models/api_response.py
mparticle/models/api_response_errors.py
mparticle/models/app_event.py
mparticle/models/application_information.py
mparticle/models/application_state_transition_event.py
mparticle/models/attribution_info.py
mparticle/models/batch.py
mparticle/models/batch_context.py
mparticle/models/breadcrumb_event.py
mparticle/models/ccpa_consent_state.py
mparticle/models/commerce_event.py
mparticle/models/consent_state.py
mparticle/models/crash_report_event.py
mparticle/models/data_plan_context.py
mparticle/models/device_current_state.py
mparticle/models/device_information.py
mparticle/models/event_base.py
mparticle/models/event_data.py
mparticle/models/first_run_event.py
mparticle/models/gdpr_consent_state.py
mparticle/models/geo_location.py
mparticle/models/media_info.py
mparticle/models/network_performance_event.py
mparticle/models/opt_out_event.py
mparticle/models/product.py
mparticle/models/product_action.py
mparticle/models/product_impression.py
mparticle/models/profile_event.py
mparticle/models/promotion.py
mparticle/models/promotion_action.py
mparticle/models/push_message_event.py
mparticle/models/push_registration_event.py
mparticle/models/screen_view_event.py
mparticle/models/session_end_event.py
mparticle/models/session_start_event.py
mparticle/models/shopping_cart.py
mparticle/models/source_information.py
mparticle/models/user_attribute_change_event.py
mparticle/models/user_identities.py
test/__init__.py
test/test_api_client.py
test/test_api_response.py
test/test_api_response_errors.py
test/test_app_event.py
test/test_application_information.py
test/test_application_state_transition_event.py
test/test_attribution_info.py
test/test_batch.py
test/test_batch_context.py
test/test_breadcrumb_event.py
test/test_ccpa_consent_state.py
test/test_commerce_event.py
mparticle-0.16.1.dist-info/LICENSE
mparticle-0.16.1.dist-info/METADATA
mparticle-0.16.1.dist-info/WHEEL
mparticle-0.16.1.dist-info/top_level.txt
mparticle-0.16.1.dist-info/RECORD
