Metadata-Version: 2.1
Name: mparticle
Version: 0.16.1
Summary: Python client for the mParticle platform
Home-page: https://github.com/mParticle/mparticle-python-sdk
Author: Sam Dozor
Author-email: support@mparticle.com
License: Apache 2.0
Keywords: mparticle analytics marketing
Classifier: Development Status :: 5 - Production/Stable
Classifier: Intended Audience :: Developers
Classifier: License :: OSI Approved :: Apache Software License
Classifier: Programming Language :: Python
Classifier: Programming Language :: Python :: 2.7
Classifier: Programming Language :: Python :: 3
Classifier: Programming Language :: Python :: 3.3
Classifier: Programming Language :: Python :: 3.4
Classifier: Programming Language :: Python :: 3.5
Classifier: Programming Language :: Python :: 3.6
License-File: LICENSE
Requires-Dist: urllib3 (>=1.15)
Requires-Dist: six (>=1.10)
Requires-Dist: certifi
Requires-Dist: python-dateutil
